morph_utils/__init__.py
morph_utils/access_query.py
morph_utils/ccf.py
morph_utils/colors.py
morph_utils/graph_traversal.py
morph_utils/measurements.py
morph_utils/modifications.py
morph_utils/proj_mat_utils.py
morph_utils/query.py
morph_utils/templates.py
morph_utils/validation.py
morph_utils/visuals.py
morph_utils/data/AIT21.0_colors_cluster.csv
morph_utils/data/AIT21.0_colors_subclass.csv
morph_utils/data/AIT21.0_colors_supertype.csv
morph_utils/data/WB_colorpal_cluster.csv
morph_utils/data/__init__.py
morph_utils/data/annotation_10.nrrd
morph_utils/data/annotation_10.txt
morph_utils/data/ccf_structure_acronym_by_id.json
morph_utils/data/ccf_structure_graph.csv
morph_utils/data/ccf_structure_name_map.json
morph_utils/data/human_average_layer_depths.json
morph_utils/data/mouse_average_layer_depths.json
morph_utils/data/structure_descendent_list.json
morph_utils/executable_scripts/__init__.py
morph_utils/executable_scripts/aggregate_single_cell_projection_csvs.py
morph_utils/executable_scripts/distance_between_nodes_for_directory.py
morph_utils/executable_scripts/full_morphology_soma_correction.py
morph_utils/executable_scripts/local_crop_ccf_swc_directory.py
morph_utils/executable_scripts/move_somas_to_left_hemisphere_swc_directory.py
morph_utils/executable_scripts/projection_matrix_for_single_cell.py
morph_utils/executable_scripts/projection_matrix_from_swc_directory.py
morph_utils/executable_scripts/sort_morphology_ids.py
morph_utils/executable_scripts/validate_swc_dir.py
morph_utils-1.5.6.dist-info/METADATA
morph_utils-1.5.6.dist-info/WHEEL
morph_utils-1.5.6.dist-info/entry_points.txt
morph_utils-1.5.6.dist-info/top_level.txt
morph_utils-1.5.6.dist-info/RECORD
