Metadata-Version: 2.1
Name: morph-utils
Version: 1.5.6
Summary: Functions for common and not so common morphology operations
Home-page: https://github.com/MatthewMallory/morph_utils
Author: Matthew Mallory
Author-email: matt.mallory@alleninstitute.org
Requires-Dist: argschema
Requires-Dist: matplotlib
Requires-Dist: neuron-morphology
Requires-Dist: numpy
Requires-Dist: pandas <=2.2.3
Requires-Dist: pytest
Requires-Dist: scikit-learn
Requires-Dist: scipy
